odoogap_mtd/__init__.py
odoogap_mtd/mtd_headers.py
odoogap_mtd-0.1.1.dist-info/LICENSE
odoogap_mtd-0.1.1.dist-info/METADATA
odoogap_mtd-0.1.1.dist-info/WHEEL
odoogap_mtd-0.1.1.dist-info/top_level.txt
odoogap_mtd-0.1.1.dist-info/RECORD
