Metadata-Version: 2.1
Name: odoogap-mtd
Version: 0.1.1
Summary: MTD Library For OdooGAP
Home-page: https://github.com/odoogap/mtd_library
Author: OdooGap
Author-email: 
License: UNKNOWN
Platform: UNKNOWN
Classifier: Programming Language :: Python :: 3
Classifier: License :: OSI Approved :: MIT License
Classifier: Operating System :: OS Independent
Requires-Python: >=3.6
